<?xml version="1.0" encoding="utf-8" ?>
<dwsync>
<file name="anchor.gif" server="vectec.org/public_html/" local="128557870800000000" remote="128557870800000000" />
<file name="anchor_symbol.gif" server="vectec.org/public_html/" local="128557870800000000" remote="128557870800000000" />
<file name="backcolor.gif" server="vectec.org/public_html/" local="128557870800000000" remote="128557870800000000" />
<file name="bold.gif" server="vectec.org/public_html/" local="128557870800000000" remote="128557870800000000" />
<file name="bold_de_se.gif" server="vectec.org/public_html/" local="128557870800000000" remote="128557870800000000" />
<file name="bold_es.gif" server="vectec.org/public_html/" local="128557870800000000" remote="128557870800000000" />
<file name="bold_fr.gif" server="vectec.org/public_html/" local="128557870800000000" remote="128557870800000000" />
<file name="bold_ru.gif" server="vectec.org/public_html/" local="128557870800000000" remote="128557870800000000" />
<file name="bold_tw.gif" server="vectec.org/public_html/" local="128557870800000000" remote="128557870800000000" />
<file name="browse.gif" server="vectec.org/public_html/" local="128557870800000000" remote="128557870800000000" />
<file name="bullist.gif" server="vectec.org/public_html/" local="128557870800000000" remote="128557870800000000" />
<file name="button_menu.gif" server="vectec.org/public_html/" local="128557870800000000" remote="128557870800000000" />
<file name="buttons.gif" server="vectec.org/public_html/" local="128557870800000000" remote="128557870800000000" />
<file name="cancel_button_bg.gif" server="vectec.org/public_html/" local="128557870800000000" remote="128557870800000000" />
<file name="charmap.gif" server="vectec.org/public_html/" local="128557870800000000" remote="128557870800000000" />
<file name="cleanup.gif" server="vectec.org/public_html/" local="128557870800000000" remote="128557870800000000" />
<file name="close.gif" server="vectec.org/public_html/" local="128557870800000000" remote="128557870800000000" />
<file name="code.gif" server="vectec.org/public_html/" local="128557870800000000" remote="128557870800000000" />
<file name="color.gif" server="vectec.org/public_html/" local="128557870800000000" remote="128557870800000000" />
<file name="colors.jpg" server="vectec.org/public_html/" local="128557870800000000" remote="128557870800000000" />
<file name="copy.gif" server="vectec.org/public_html/" local="128557870800000000" remote="128557870800000000" />
<file name="custom_1.gif" server="vectec.org/public_html/" local="128557870800000000" remote="128557870800000000" />
<file name="cut.gif" server="vectec.org/public_html/" local="128557870800000000" remote="128557870800000000" />
<file name="forecolor.gif" server="vectec.org/public_html/" local="128557870800000000" remote="128557870800000000" />
<file name="help.gif" server="vectec.org/public_html/" local="128557870800000000" remote="128557870800000000" />
<file name="hr.gif" server="vectec.org/public_html/" local="128557870800000000" remote="128557870800000000" />
<file name="image.gif" server="vectec.org/public_html/" local="128557870800000000" remote="128557870800000000" />
<file name="indent.gif" server="vectec.org/public_html/" local="128557870800000000" remote="128557870800000000" />
<file name="insert_button_bg.gif" server="vectec.org/public_html/" local="128557870800000000" remote="128557870800000000" />
<file name="italic.gif" server="vectec.org/public_html/" local="128557870800000000" remote="128557870800000000" />
<file name="italic_de_se.gif" server="vectec.org/public_html/" local="128557870800000000" remote="128557870800000000" />
<file name="italic_es.gif" server="vectec.org/public_html/" local="128557870800000000" remote="128557870800000000" />
<file name="italic_ru.gif" server="vectec.org/public_html/" local="128557870800000000" remote="128557870800000000" />
<file name="italic_tw.gif" server="vectec.org/public_html/" local="128557870800000000" remote="128557870800000000" />
<file name="justifycenter.gif" server="vectec.org/public_html/" local="128557870800000000" remote="128557870800000000" />
<file name="justifyfull.gif" server="vectec.org/public_html/" local="128557870800000000" remote="128557870800000000" />
<file name="justifyleft.gif" server="vectec.org/public_html/" local="128557870800000000" remote="128557870800000000" />
<file name="justifyright.gif" server="vectec.org/public_html/" local="128557870800000000" remote="128557870800000000" />
<file name="link.gif" server="vectec.org/public_html/" local="128557870800000000" remote="128557870800000000" />
<file name="menu_check.gif" server="vectec.org/public_html/" local="128557870800000000" remote="128557870800000000" />
<file name="newdocument.gif" server="vectec.org/public_html/" local="128557870800000000" remote="128557870800000000" />
<file name="numlist.gif" server="vectec.org/public_html/" local="128557870800000000" remote="128557870800000000" />
<file name="opacity.png" server="vectec.org/public_html/" local="128557870800000000" remote="128557870800000000" />
<file name="outdent.gif" server="vectec.org/public_html/" local="128557870800000000" remote="128557870800000000" />
<file name="paste.gif" server="vectec.org/public_html/" local="128557870800000000" remote="128557870800000000" />
<file name="redo.gif" server="vectec.org/public_html/" local="128557870800000000" remote="128557870800000000" />
<file name="removeformat.gif" server="vectec.org/public_html/" local="128557870800000000" remote="128557870800000000" />
<file name="separator.gif" server="vectec.org/public_html/" local="128557870800000000" remote="128557870800000000" />
<file name="spacer.gif" server="vectec.org/public_html/" local="128557870800000000" remote="128557870800000000" />
<file name="statusbar_resize.gif" server="vectec.org/public_html/" local="128557870800000000" remote="128557870800000000" />
<file name="strikethrough.gif" server="vectec.org/public_html/" local="128557870800000000" remote="128557870800000000" />
<file name="sub.gif" server="vectec.org/public_html/" local="128557870800000000" remote="128557870800000000" />
<file name="sup.gif" server="vectec.org/public_html/" local="128557870800000000" remote="128557870800000000" />
<file name="underline.gif" server="vectec.org/public_html/" local="128557870800000000" remote="128557870800000000" />
<file name="underline_es.gif" server="vectec.org/public_html/" local="128557870800000000" remote="128557870800000000" />
<file name="underline_fr.gif" server="vectec.org/public_html/" local="128557870800000000" remote="128557870800000000" />
<file name="underline_ru.gif" server="vectec.org/public_html/" local="128557870800000000" remote="128557870800000000" />
<file name="underline_tw.gif" server="vectec.org/public_html/" local="128557870800000000" remote="128557870800000000" />
<file name="undo.gif" server="vectec.org/public_html/" local="128557870800000000" remote="128557870800000000" />
<file name="unlink.gif" server="vectec.org/public_html/" local="128557870800000000" remote="128557870800000000" />
<file name="visualaid.gif" server="vectec.org/public_html/" local="128557870800000000" remote="128557870800000000" />
</dwsync>