<?xml version="1.0" encoding="utf-8" ?>
<dwsync>
<file name="barcode.php" server="vectec.org/public_html/" local="128558617800000000" remote="128558617800000000" />
<file name="c128aobject.php" server="vectec.org/public_html/" local="128558617800000000" remote="128558617800000000" />
<file name="c128bobject.php" server="vectec.org/public_html/" local="128558617800000000" remote="128558617800000000" />
<file name="c128cobject.php" server="vectec.org/public_html/" local="128558617800000000" remote="128558617800000000" />
<file name="c39object.php" server="vectec.org/public_html/" local="128558617800000000" remote="128558617800000000" />
<file name="i25object.php" server="vectec.org/public_html/" local="128558617800000000" remote="128558617800000000" />
<file name="image.php" server="vectec.org/public_html/" local="128558617800000000" remote="128558617800000000" />
<file name="lesser.txt" server="vectec.org/public_html/" local="128558617800000000" remote="128558617800000000" />
</dwsync>