<?xml version="1.0" encoding="utf-8" ?>
<dwsync>
<file name="browser.css" server="vectec.org/public_html/" local="128559489000000000" remote="128559489000000000" />
<file name="browser.html" server="vectec.org/public_html/" local="128559489000000000" remote="128559489000000000" />
<file name="frmactualfolder.html" server="vectec.org/public_html/" local="128559489000000000" remote="128559489000000000" />
<file name="frmcreatefolder.html" server="vectec.org/public_html/" local="128559489000000000" remote="128559489000000000" />
<file name="frmfolders.html" server="vectec.org/public_html/" local="128559489000000000" remote="128559489000000000" />
<file name="frmresourceslist.html" server="vectec.org/public_html/" local="128559489000000000" remote="128559489000000000" />
<file name="frmresourcetype.html" server="vectec.org/public_html/" local="128559489000000000" remote="128559489000000000" />
<file name="frmupload.html" server="vectec.org/public_html/" local="128559489000000000" remote="128559489000000000" />
</dwsync>