<?xml version="1.0" encoding="utf-8" ?>
<dwsync>
<file name="sample01.cfm" server="vectec.org/public_html/" local="128559489000000000" remote="128559489000000000" />
<file name="sample01_mx.cfm" server="vectec.org/public_html/" local="128559489000000000" remote="128559489000000000" />
<file name="sample02.cfm" server="vectec.org/public_html/" local="128559489000000000" remote="128559489000000000" />
<file name="sample02_mx.cfm" server="vectec.org/public_html/" local="128559489000000000" remote="128559489000000000" />
<file name="sample03.cfm" server="vectec.org/public_html/" local="128559489000000000" remote="128559489000000000" />
<file name="sample03_mx.cfm" server="vectec.org/public_html/" local="128559489000000000" remote="128559489000000000" />
<file name="sample04.cfm" server="vectec.org/public_html/" local="128559489000000000" remote="128559489000000000" />
<file name="sample04_mx.cfm" server="vectec.org/public_html/" local="128559489000000000" remote="128559489000000000" />
<file name="sampleposteddata.cfm" server="vectec.org/public_html/" local="128559489000000000" remote="128559489000000000" />
</dwsync>